DriveDownloader/__init__.py
DriveDownloader/downloader.py
DriveDownloader/netdrives/__init__.py
DriveDownloader/netdrives/basedrive.py
DriveDownloader/netdrives/build.py
DriveDownloader/netdrives/directlink.py
DriveDownloader/netdrives/dropbox.py
DriveDownloader/netdrives/googledrive.py
DriveDownloader/netdrives/onedrive.py
DriveDownloader/netdrives/sharepoint.py
DriveDownloader/pydrive2/__init__.py
DriveDownloader/pydrive2/apiattr.py
DriveDownloader/pydrive2/auth.py
DriveDownloader/pydrive2/drive.py
DriveDownloader/pydrive2/files.py
DriveDownloader/pydrive2/settings.py
DriveDownloader/pydrive2/fs/__init__.py
DriveDownloader/pydrive2/fs/spec.py
DriveDownloader/pydrive2/fs/utils.py
DriveDownloader/utils/__init__.py
DriveDownloader/utils/misc.py
DriveDownloader/utils/multithread.py
DriveDownloader-1.6.0.post1.dist-info/LICENSE
DriveDownloader-1.6.0.post1.dist-info/METADATA
DriveDownloader-1.6.0.post1.dist-info/WHEEL
DriveDownloader-1.6.0.post1.dist-info/entry_points.txt
DriveDownloader-1.6.0.post1.dist-info/top_level.txt
DriveDownloader-1.6.0.post1.dist-info/RECORD
